{
  "config": "{\"version\":\"5.47\",\"themeCollection\":{\"baseTheme\":{\"name\":\"CY23SU08\",\"version\":\"5.48\",\"type\":2}},\"activeSectionIndex\":0,\"defaultDrillFilterOtherVisuals\":true,\"slowDataSourceSettings\":{\"isCrossHighlightingDisabled\":false,\"isSlicerSelectionsButtonEnabled\":false,\"isFilterSelectionsButtonEnabled\":false,\"isFieldWellButtonEnabled\":false,\"isApplyAllButtonEnabled\":false},\"linguisticSchemaSyncVersion\":2,\"settings\":{\"useNewFilterPaneExperience\":true,\"allowChangeFilterTypes\":true,\"useStylableVisualContainerHeader\":true,\"queryLimitOption\":6,\"exportDataMode\":1,\"useDefaultAggregateDisplayName\":true,\"useEnhancedTooltips\":true},\"objects\":{\"section\":[{\"properties\":{\"verticalAlignment\":{\"expr\":{\"Literal\":{\"Value\":\"'Top'\"}}}}}],\"outspacePane\":[{\"properties\":{\"expanded\":{\"expr\":{\"Literal\":{\"Value\":\"false\"}}}}}]}}",
  "layoutOptimization": 0,
  "resourcePackages": [
    {
      "resourcePackage": {
        "disabled": false,
        "items": [
          {
            "name": "CY23SU08",
            "path": "BaseThemes/CY23SU08.json",
            "type": 202
          }
        ],
        "name": "SharedResources",
        "type": 2
      }
    }
  ],
  "sections": [
    {
      "config": "{}",
      "displayName": "Page 1",
      "displayOption": 1,
      "filters": "[]",
      "height": 720.00,
      "name": "ReportSection",
      "visualContainers": [
        {
          "config": "{\"name\":\"21add1930255137613d2\",\"layouts\":[{\"id\":0,\"position\":{\"x\":0,\"y\":212.98013245033113,\"z\":0,\"width\":1236.5562913907286,\"height\":429.13907284768214,\"tabOrder\":0}}],\"singleVisual\":{\"visualType\":\"tableEx\",\"projections\":{\"Values\":[{\"queryRef\":\"Sheet1.name\"},{\"queryRef\":\"Sheet1.Month Name\"},{\"queryRef\":\"Sum(Sheet1.id)\"},{\"queryRef\":\"Sheet1.Type\"},{\"queryRef\":\"Sheet1.IBU\"},{\"queryRef\":\"Sheet1.dis\"},{\"queryRef\":\"Sheet1.Customer\"},{\"queryRef\":\"Sum(Sheet1.Band)\"},{\"queryRef\":\"Sheet1.StatusChange2\"},{\"queryRef\":\"Sheet1.StatusChange\"}]},\"prototypeQuery\":{\"Version\":2,\"From\":[{\"Name\":\"s\",\"Entity\":\"Sheet1\",\"Type\":0}],\"Select\":[{\"Column\":{\"Expression\":{\"SourceRef\":{\"Source\":\"s\"}},\"Property\":\"name\"},\"Name\":\"Sheet1.name\",\"NativeReferenceName\":\"Name\"},{\"Column\":{\"Expression\":{\"SourceRef\":{\"Source\":\"s\"}},\"Property\":\"id\"},\"Name\":\"Sum(Sheet1.id)\",\"NativeReferenceName\":\"id\"},{\"Column\":{\"Expression\":{\"SourceRef\":{\"Source\":\"s\"}},\"Property\":\"Type\"},\"Name\":\"Sheet1.Type\",\"NativeReferenceName\":\"Type\"},{\"Column\":{\"Expression\":{\"SourceRef\":{\"Source\":\"s\"}},\"Property\":\"IBU\"},\"Name\":\"Sheet1.IBU\",\"NativeReferenceName\":\"IBU\"},{\"Column\":{\"Expression\":{\"SourceRef\":{\"Source\":\"s\"}},\"Property\":\"dis\"},\"Name\":\"Sheet1.dis\",\"NativeReferenceName\":\"dis\"},{\"Column\":{\"Expression\":{\"SourceRef\":{\"Source\":\"s\"}},\"Property\":\"Customer\"},\"Name\":\"Sheet1.Customer\",\"NativeReferenceName\":\"Customer\"},{\"Column\":{\"Expression\":{\"SourceRef\":{\"Source\":\"s\"}},\"Property\":\"Band\"},\"Name\":\"Sum(Sheet1.Band)\",\"NativeReferenceName\":\"Band\"},{\"Column\":{\"Expression\":{\"SourceRef\":{\"Source\":\"s\"}},\"Property\":\"Month Name\"},\"Name\":\"Sheet1.Month Name\",\"NativeReferenceName\":\"Month Name\"},{\"Column\":{\"Expression\":{\"SourceRef\":{\"Source\":\"s\"}},\"Property\":\"StatusChange2\"},\"Name\":\"Sheet1.StatusChange2\",\"NativeReferenceName\":\"StatusChange2\"},{\"Column\":{\"Expression\":{\"SourceRef\":{\"Source\":\"s\"}},\"Property\":\"StatusChange\"},\"Name\":\"Sheet1.StatusChange\",\"NativeReferenceName\":\"StatusChange\"}]},\"columnProperties\":{\"Sheet1.name\":{\"displayName\":\"Name\"}},\"drillFilterOtherVisuals\":true,\"objects\":{\"values\":[{\"properties\":{\"fontSize\":{\"expr\":{\"Literal\":{\"Value\":\"16D\"}}}}}]}}}",
          "filters": "[]",
          "height": 429.14,
          "width": 1236.56,
          "x": 0.00,
          "y": 212.98,
          "z": 0.00
        },
        {
          "config": "{\"name\":\"2c2525e3e6a6b0d68a00\",\"layouts\":[{\"id\":0,\"position\":{\"x\":464.424778761062,\"y\":47.197640117994105,\"z\":2000,\"width\":252.9793510324484,\"height\":137.81710914454277,\"tabOrder\":2000}}],\"singleVisual\":{\"visualType\":\"slicer\",\"projections\":{\"Values\":[{\"queryRef\":\"Sheet1.Month Name\",\"active\":true}]},\"prototypeQuery\":{\"Version\":2,\"From\":[{\"Name\":\"s\",\"Entity\":\"Sheet1\",\"Type\":0}],\"Select\":[{\"Column\":{\"Expression\":{\"SourceRef\":{\"Source\":\"s\"}},\"Property\":\"Month Name\"},\"Name\":\"Sheet1.Month Name\",\"NativeReferenceName\":\"Month Name\"}]},\"drillFilterOtherVisuals\":true,\"objects\":{\"data\":[{\"properties\":{\"mode\":{\"expr\":{\"Literal\":{\"Value\":\"'Dropdown'\"}}}}}],\"general\":[{\"properties\":{\"filter\":{\"filter\":{\"Version\":2,\"From\":[{\"Name\":\"s\",\"Entity\":\"Sheet1\",\"Type\":0}],\"Where\":[{\"Condition\":{\"In\":{\"Expressions\":[{\"Column\":{\"Expression\":{\"SourceRef\":{\"Source\":\"s\"}},\"Property\":\"Month Name\"}}],\"Values\":[[{\"Literal\":{\"Value\":\"'February'\"}}]]}}}]}}}}],\"selection\":[{\"properties\":{\"selectAllCheckboxEnabled\":{\"expr\":{\"Literal\":{\"Value\":\"true\"}}}}}]}}}",
          "filters": "[]",
          "height": 137.82,
          "width": 252.98,
          "x": 464.42,
          "y": 47.20,
          "z": 2000.00
        },
        {
          "config": "{\"name\":\"728b846742e70e1733ad\",\"layouts\":[{\"id\":0,\"position\":{\"x\":813,\"y\":35,\"width\":335,\"height\":150,\"z\":3000,\"tabOrder\":3000}}],\"singleVisual\":{\"visualType\":\"slicer\",\"projections\":{\"Values\":[{\"queryRef\":\"Sheet1.name\",\"active\":true}]},\"prototypeQuery\":{\"Version\":2,\"From\":[{\"Name\":\"s\",\"Entity\":\"Sheet1\",\"Type\":0}],\"Select\":[{\"Column\":{\"Expression\":{\"SourceRef\":{\"Source\":\"s\"}},\"Property\":\"name\"},\"Name\":\"Sheet1.name\",\"NativeReferenceName\":\"name\"}]},\"drillFilterOtherVisuals\":true,\"objects\":{\"data\":[{\"properties\":{\"mode\":{\"expr\":{\"Literal\":{\"Value\":\"'Basic'\"}}}}}],\"general\":[{\"properties\":{}}]}}}",
          "filters": "[]",
          "height": 150.00,
          "width": 335.00,
          "x": 813.00,
          "y": 35.00,
          "z": 3000.00
        },
        {
          "config": "{\"name\":\"d8d92252eb3c117eed23\",\"layouts\":[{\"id\":0,\"position\":{\"x\":0,\"y\":47.197640117994105,\"z\":1000,\"width\":349.26253687315636,\"height\":137.81710914454277,\"tabOrder\":1000}}],\"singleVisual\":{\"visualType\":\"slicer\",\"projections\":{\"Values\":[{\"queryRef\":\"Sheet1.id\",\"active\":true}]},\"prototypeQuery\":{\"Version\":2,\"From\":[{\"Name\":\"s\",\"Entity\":\"Sheet1\",\"Type\":0}],\"Select\":[{\"Column\":{\"Expression\":{\"SourceRef\":{\"Source\":\"s\"}},\"Property\":\"id\"},\"Name\":\"Sheet1.id\",\"NativeReferenceName\":\"id\"}]},\"drillFilterOtherVisuals\":true,\"objects\":{\"data\":[{\"properties\":{\"mode\":{\"expr\":{\"Literal\":{\"Value\":\"'Dropdown'\"}}}}}],\"general\":[{\"properties\":{}}],\"selection\":[{\"properties\":{\"selectAllCheckboxEnabled\":{\"expr\":{\"Literal\":{\"Value\":\"true\"}}}}}]}}}",
          "filters": "[]",
          "height": 137.82,
          "width": 349.26,
          "x": 0.00,
          "y": 47.20,
          "z": 1000.00
        }
      ],
      "width": 1280.00
    }
  ]
}